{
  "$schema": "./node_modules/@angular/cli/lib/config/schema.json",
  "version": 1,
  "newProjectRoot": "projects",
  "projects": {
    "ngx-formly-ng-zorro": {
      "projectType": "application",
      "schematics": {
        "@schematics/angular:component": {
          "style": "less"
        }
      },
      "root": "",
      "sourceRoot": "src",
      "prefix": "app",
      "architect": {
        "build": {
          "builder": "@angular-devkit/build-angular:browser",
          "options": {
            "outputPath": "dist/ngx-formly-ng-zorro",
            "index": "src/index.html",
            "main": "src/main.ts",
            "polyfills": "src/polyfills.ts",
            "tsConfig": "tsconfig.app.json",
            "aot": true,
            "assets": [
              "src/favicon.ico",
              "src/assets"
            ],
            "styles": [
              "./node_modules/ng-zorro-antd/ng-zorro-antd.min.css",
              "src/styles.less"
            ],
            "scripts": []
          },
          "configurations": {
            "production": {
              "fileReplacements": [
                {
                  "replace": "src/environments/environment.ts",
                  "with": "src/environments/environment.prod.ts"
                }
              ],
              "optimization": true,
              "outputHashing": "all",
              "sourceMap": false,
              "namedChunks": false,
              "extractLicenses": true,
              "vendorChunk": false,
              "buildOptimizer": true,
              "budgets": [
                {
                  "type": "initial",
                  "maximumWarning": "2mb",
                  "maximumError": "5mb"
                },
                {
                  "type": "anyComponentStyle",
                  "maximumWarning": "6kb",
                  "maximumError": "10kb"
                }
              ]
            },
            "development":{
              "buildOptimizer": false,
              "sourceMap":true,
              "optimization": false,
"vendorChunk": true ,
"extractLicenses": false
            }
           
          }
        },
        "serve": {
          "builder": "@angular-devkit/build-angular:dev-server",
          
          "options": {
            "browserTarget": "ngx-formly-ng-zorro:build"
            
          },
          
          "configurations": {
            
            "production": {
              "browserTarget": "ngx-formly-ng-zorro:build:production"
             
            },
            "development":{}
         
          },
          "defaultConfiguration": "development"
        },
        "extract-i18n": {
          "builder": "@angular-devkit/build-angular:extract-i18n",
          "options": {
            "browserTarget": "ngx-formly-ng-zorro:build"
          }
        },
        "test": {
          "builder": "@angular-devkit/build-angular:karma",
          "options": {
            "main": "src/test.ts",
            "polyfills": "src/polyfills.ts",
            "tsConfig": "tsconfig.spec.json",
            "karmaConfig": "karma.conf.js",
            "assets": [
              "src/favicon.ico",
              "src/assets"
            ],
            "styles": [
              "./node_modules/ng-zorro-antd/ng-zorro-antd.min.css",
              "src/styles.less"
            ],
            "scripts": []
          }
        },
        "lint": {
          "builder": "@angular-devkit/build-angular:tslint",
          "options": {
            "tsConfig": [
              "tsconfig.app.json",
              "tsconfig.spec.json",
              "e2e/tsconfig.json"
            ],
            "exclude": [
              "**/node_modules/**"
            ]
          }
        },
        "e2e": {
          "builder": "@angular-devkit/build-angular:protractor",
          "options": {
            "protractorConfig": "e2e/protractor.conf.js",
            "devServerTarget": "ngx-formly-ng-zorro:serve"
          },
          "configurations": {
            "production": {
              "devServerTarget": "ngx-formly-ng-zorro:serve:production"
            }
          }
        }
      }
    },
    "NgxFormlyNgZorro": {
      "projectType": "library",
      "root": "projects/formly-ng-zorro",
      "sourceRoot": "projects/formly-ng-zorro/src",
      "prefix": "lib",
      "architect": {
        "build": {
          "builder": "@angular-devkit/build-angular:ng-packagr",
          "options": {
            "tsConfig": "projects/formly-ng-zorro/tsconfig.lib.json",
            "project": "projects/formly-ng-zorro/ng-package.json"
          },
          "configurations": {
            "production": {
              "tsConfig": "projects/formly-ng-zorro/tsconfig.lib.prod.json"
            }
          }
        },
        "test": {
          "builder": "@angular-devkit/build-angular:karma",
          "options": {
            "main": "projects/formly-ng-zorro/src/test.ts",
            "tsConfig": "projects/formly-ng-zorro/tsconfig.spec.json",
            "karmaConfig": "projects/formly-ng-zorro/karma.conf.js"
          }
        },
        "lint": {
          "builder": "@angular-devkit/build-angular:tslint",
          "options": {
            "tsConfig": [
              "projects/formly-ng-zorro/tsconfig.lib.json",
              "projects/formly-ng-zorro/tsconfig.spec.json"
            ],
            "exclude": [
              "**/node_modules/**"
            ]
          }
        }
      }
    }
  },
  "defaultProject": "ngx-formly-ng-zorro"
}
